openbb_tmx/__init__.py
openbb_tmx/models/__init__.py
openbb_tmx/models/available_indices.py
openbb_tmx/models/bond_prices.py
openbb_tmx/models/calendar_earnings.py
openbb_tmx/models/company_filings.py
openbb_tmx/models/company_news.py
openbb_tmx/models/equity_historical.py
openbb_tmx/models/equity_profile.py
openbb_tmx/models/equity_quote.py
openbb_tmx/models/equity_search.py
openbb_tmx/models/etf_countries.py
openbb_tmx/models/etf_holdings.py
openbb_tmx/models/etf_info.py
openbb_tmx/models/etf_search.py
openbb_tmx/models/etf_sectors.py
openbb_tmx/models/gainers.py
openbb_tmx/models/historical_dividends.py
openbb_tmx/models/index_constituents.py
openbb_tmx/models/index_sectors.py
openbb_tmx/models/index_snapshots.py
openbb_tmx/models/insider_trading.py
openbb_tmx/models/options_chains.py
openbb_tmx/models/price_target_consensus.py
openbb_tmx/models/treasury_prices.py
openbb_tmx/py.typed
openbb_tmx/utils/__init__.py
openbb_tmx/utils/gql.py
openbb_tmx/utils/helpers.py
openbb_tmx-1.4.1.dist-info/METADATA
openbb_tmx-1.4.1.dist-info/WHEEL
openbb_tmx-1.4.1.dist-info/entry_points.txt
openbb_tmx-1.4.1.dist-info/RECORD
