Metadata-Version: 2.4
Name: openbb-tmx
Version: 1.4.1
Summary: Unofficial TMX data provider extension for the OpenBB Platform - Public Canadian markets data for Python and Fast API.
License: AGPL-3.0-only
Author: OpenBB
Author-email: hello@openbb.co
Requires-Python: >=3.10,<3.14
Classifier: License :: OSI Approved :: GNU Affero General Public License v3
Classifier: Programming Language :: Python :: 3
Classifier: Programming Language :: Python :: 3.10
Classifier: Programming Language :: Python :: 3.11
Classifier: Programming Language :: Python :: 3.12
Classifier: Programming Language :: Python :: 3.13
Requires-Dist: aiohttp-client-cache (>=0.11.0,<0.12.0)
Requires-Dist: aiosqlite (>=0.20.0,<0.21.0)
Requires-Dist: exchange-calendars (>=4.5.4,<5.0.0)
Requires-Dist: openbb-core (>=1.5.7,<2.0.0)
Requires-Dist: random-user-agent (>=1.0.1,<2.0.0)
